MANIFEST.in
README.rst
qQuickLicence.txt
setup.cfg
setup.py
Eden.egg-info/PKG-INFO
Eden.egg-info/SOURCES.txt
Eden.egg-info/dependency_links.txt
Eden.egg-info/requires.txt
Eden.egg-info/top_level.txt
eden/__init__.py
eden/nodes.store
eden/views.store
eden/edenExtra/__init__.py
eden/edenExtra/tweakers.py
eden/edenExtra/kivy/__init__.py
eden/edenExtra/kivy/tweakers.py
eden/edenExtra/winForms/__init__.py
eden/edenExtra/winForms/tweakers.py
eden/edenLib/__init__.py
eden/edenLib/base.py
eden/edenLib/module.py
eden/edenLib/node.py
eden/edenLib/panel.py
eden/edenLib/platform.py
eden/edenLib/store.py
eden/edenLib/util.py
eden/edenLib/view.py
eden/edenLib/xml.py
eden/edenLib/icons/bookQuestion.bmp
eden/edenLib/icons/browse.bmp
eden/edenLib/icons/downArrow.bmp
eden/edenLib/icons/downArrowPlus.bmp
eden/edenLib/icons/downCrossMinus.bmp
eden/edenLib/icons/index.bmp
eden/edenLib/icons/information.bmp
eden/edenLib/icons/lamp.bmp
eden/edenLib/icons/leftArrow.bmp
eden/edenLib/icons/leftArrowMinus.bmp
eden/edenLib/icons/leftArrowPlus.bmp
eden/edenLib/icons/leftArrowSmall.bmp
eden/edenLib/icons/leftCross.bmp
eden/edenLib/icons/leftCrossMinus.bmp
eden/edenLib/icons/loadBarGraph.bmp
eden/edenLib/icons/loadTabs.bmp
eden/edenLib/icons/microscope.bmp
eden/edenLib/icons/microscopeExclamation.bmp
eden/edenLib/icons/pause.bmp
eden/edenLib/icons/play.bmp
eden/edenLib/icons/record.bmp
eden/edenLib/icons/rightArrow.bmp
eden/edenLib/icons/rightArrowPlus.bmp
eden/edenLib/icons/rightArrowSmall.bmp
eden/edenLib/icons/rightCrossMinus.bmp
eden/edenLib/icons/saveBarGraph.bmp
eden/edenLib/icons/saveTabs.bmp
eden/edenLib/icons/saveText.bmp
eden/edenLib/icons/stop.bmp
eden/edenLib/icons/upArrow.bmp
eden/edenLib/icons/upArrowPlus.bmp
eden/edenLib/icons/upCrossMinus.bmp
eden/edenLib/kivy/__init__.py
eden/edenLib/kivy/panel.py
eden/edenLib/kivy/platform.py
eden/edenLib/kivy/util.py
eden/edenLib/kivy/view.py
eden/edenLib/openGl/__init__.py
eden/edenLib/openGl/decal.txt
eden/edenLib/openGl/fonts.txt
eden/edenLib/openGl/openGLDebug.py
eden/edenLib/openGl/panel.py
eden/edenLib/openGl/platform.py
eden/edenLib/openGl/scene.py
