Metadata-Version: 1.1
Name: Eden
Version: 2.1.14
Summary: Eden - Event Driven Evaluation Nodes, tested with Kivy 1.9.0
Home-page: http://www.qquick.org
Author: Jacques de Hooge
Author-email: jacques.de.hooge@qquick.org
License: qQuickLicence
Keywords: eden,kivy,winforms,observer,functional
Platform: UNKNOWN
Classifier: Development Status :: 4 - Beta
Classifier: Intended Audience :: Developers
Classifier: Natural Language :: English
Classifier: License :: Other/Proprietary License
Classifier: Topic :: Software Development :: Libraries :: Python Modules
Classifier: Operating System :: OS Independent
Classifier: Programming Language :: Python :: 2.7
